zope.file-2.0-py3.11-nspkg.pth
zope/file/README.rst
zope/file/__init__.py
zope/file/adapters.py
zope/file/adapters.rst
zope/file/browser.py
zope/file/browser.rst
zope/file/browser.zcml
zope/file/configure.zcml
zope/file/contenttype.py
zope/file/contenttype.rst
zope/file/download.py
zope/file/download.rst
zope/file/event.py
zope/file/file.py
zope/file/ftesting.zcml
zope/file/i18n.py
zope/file/interfaces.py
zope/file/menus.zcml
zope/file/testing.py
zope/file/upload.py
zope/file/upload.rst
zope/file/tests/__init__.py
zope/file/tests/contents.pt
zope/file/tests/test_contenttype.py
zope/file/tests/test_doctests.py
zope/file/tests/test_upload.py
zope.file-2.0.dist-info/LICENSE.txt
zope.file-2.0.dist-info/METADATA
zope.file-2.0.dist-info/WHEEL
zope.file-2.0.dist-info/namespace_packages.txt
zope.file-2.0.dist-info/top_level.txt
zope.file-2.0.dist-info/RECORD
