Metadata-Version: 2.1
Name: zope.file
Version: 2.0
Summary: Efficient File Implementation for Zope Applications
Home-page: https://github.com/zopefoundation/zope.file
Author: Zope Corporation and Contributors
Author-email: zope-dev@zope.org
License: ZPL 2.1
Keywords: zope3 web html ui file pattern
Classifier: Development Status :: 5 - Production/Stable
Classifier: Environment :: Web Environment
Classifier: Intended Audience :: Developers
Classifier: License :: OSI Approved :: Zope Public License
Classifier: Programming Language :: Python
Classifier: Programming Language :: Python :: 3
Classifier: Programming Language :: Python :: 3.8
Classifier: Programming Language :: Python :: 3.9
Classifier: Programming Language :: Python :: 3.10
Classifier: Programming Language :: Python :: 3.11
Classifier: Programming Language :: Python :: 3.12
Classifier: Programming Language :: Python :: 3.13
Classifier: Programming Language :: Python :: Implementation :: CPython
Classifier: Programming Language :: Python :: Implementation :: PyPy
Classifier: Natural Language :: English
Classifier: Operating System :: OS Independent
Classifier: Topic :: Internet :: WWW/HTTP
Classifier: Framework :: Zope :: 3
Requires-Python: >=3.8
License-File: LICENSE.txt
Requires-Dist: setuptools
Requires-Dist: ZODB
Requires-Dist: zope.annotation
Requires-Dist: zope.component
Requires-Dist: zope.container
Requires-Dist: zope.contenttype
Requires-Dist: zope.event
Requires-Dist: zope.filerepresentation
Requires-Dist: zope.i18nmessageid
Requires-Dist: zope.lifecycleevent
Requires-Dist: zope.interface
Requires-Dist: zope.location
Requires-Dist: zope.mimetype>=2.3.0
Requires-Dist: zope.schema
Requires-Dist: zope.security>=7.1
Requires-Dist: zope.size
Provides-Extra: test
Requires-Dist: zope.browser; extra == "test"
Requires-Dist: zope.browserresource; extra == "test"
Requires-Dist: zope.publisher>=4.3.1; extra == "test"
Requires-Dist: zope.formlib; extra == "test"
Requires-Dist: zope.app.basicskin>=4.0.0; extra == "test"
Requires-Dist: zope.app.http; extra == "test"
Requires-Dist: zope.app.pagetemplate>=4.0.0; extra == "test"
Requires-Dist: zope.app.principalannotation; extra == "test"
Requires-Dist: zope.app.publication; extra == "test"
Requires-Dist: zope.app.wsgi; extra == "test"
Requires-Dist: zope.applicationcontrol; extra == "test"
Requires-Dist: zope.browser; extra == "test"
Requires-Dist: zope.browsermenu; extra == "test"
Requires-Dist: zope.copypastemove; extra == "test"
Requires-Dist: zope.login; extra == "test"
Requires-Dist: zope.password; extra == "test"
Requires-Dist: zope.principalregistry; extra == "test"
Requires-Dist: zope.proxy>=4.2.1; extra == "test"
Requires-Dist: zope.securitypolicy; extra == "test"
Requires-Dist: zope.testbrowser>=5.2; extra == "test"
Requires-Dist: zope.testing; extra == "test"
Requires-Dist: zope.testrunner; extra == "test"
Provides-Extra: browser
Requires-Dist: zope.browser; extra == "browser"
Requires-Dist: zope.browserresource; extra == "browser"
Requires-Dist: zope.publisher>=4.3.1; extra == "browser"
Requires-Dist: zope.formlib; extra == "browser"
